setup.cfg
setup.py
basketweaver/__init__.py
basketweaver/makeindex.py
basketweaver.egg-info/PKG-INFO
basketweaver.egg-info/SOURCES.txt
basketweaver.egg-info/dependency_links.txt
basketweaver.egg-info/entry_points.txt
basketweaver.egg-info/paster_plugins.txt
basketweaver.egg-info/top_level.txt
basketweaver.egg-info/zip-safe