Metadata-Version: 1.0
Name: basketweaver
Version: 0.1
Summary: Provides utilities for making your own python package index.
Home-page: http://code.google.com/p/basket-weaver/
Author: Christopher Perkins, Chris McDonough
Author-email: chris@percious.com
License: MIT
Keywords: python eggs pypi index package gz tar zip
Platform: UNKNOWN
